nonebot_plugin_YawnelleChat/__init__.py
nonebot_plugin_YawnelleChat/ai_chat.py
nonebot_plugin_YawnelleChat/config.py
nonebot_plugin_YawnelleChat/message_queue.py
nonebot_plugin_yawnellechat-0.1.0.dist-info/licenses/LICENSE
nonebot_plugin_yawnellechat-0.1.0.dist-info/METADATA
nonebot_plugin_yawnellechat-0.1.0.dist-info/WHEEL
nonebot_plugin_yawnellechat-0.1.0.dist-info/top_level.txt
nonebot_plugin_yawnellechat-0.1.0.dist-info/RECORD
