Metadata-Version: 2.4
Name: nonebot-plugin-YawnelleChat
Version: 0.1.0
Summary: 插件描述
Author-email: Wohaokunr <Wohaokunr@gmail.com>
Project-URL: Repository, https://github.com/Wohaokunr/nonebot-plugin-YawnelleChat
Requires-Python: <3.13,>=3.10
License-File: LICENSE
Requires-Dist: nonebot2<3.0.0,>=2.4.2
Requires-Dist: nonebot-adapter-onebot<3.0.0,>=2.4.6
Requires-Dist: httpx<1.0.0,>=0.27.0
Requires-Dist: openai<2.0.0,>=1.0.0
Dynamic: license-file
